<?xml version="1.0" encoding="utf-8"?>
<django-objects version="1.0"><object model="admin.logentry" pk="1"><field name="action_time" type="DateTimeField">2021-11-03T06:05:36.028000+00:00</field><field name="user" rel="ManyToOneRel" to="chapter_3.seller">1</field><field name="content_type" rel="ManyToOneRel" to="contenttypes.contenttype">12</field><field name="object_id" type="TextField">1</field><field name="object_repr" type="CharField">admin</field><field name="action_flag" type="PositiveSmallIntegerField">2</field><field name="change_message" type="TextField">[{"changed": {"fields": ["First name", "Last name"]}}]</field></object><object model="admin.logentry" pk="2"><field name="action_time" type="DateTimeField">2021-11-06T22:02:14.347000+00:00</field><field name="user" rel="ManyToOneRel" to="chapter_3.seller">1</field><field name="content_type" rel="ManyToOneRel" to="contenttypes.contenttype">13</field><field name="object_id" type="TextField">1</field><field name="object_repr" type="CharField">3.6L DI DOHC 6cyl</field><field name="action_flag" type="PositiveSmallIntegerField">2</field><field name="change_message" type="TextField">[]</field></object><object model="admin.logentry" pk="3"><field name="action_time" type="DateTimeField">2021-11-06T22:02:26.781000+00:00</field><field name="user" rel="ManyToOneRel" to="chapter_3.seller">1</field><field name="content_type" rel="ManyToOneRel" to="contenttypes.contenttype">13</field><field name="object_id" type="TextField">1</field><field name="object_repr" type="CharField">3.6L DI DOHC 6cyl</field><field name="action_flag" type="PositiveSmallIntegerField">2</field><field name="change_message" type="TextField">[]</field></object><object model="admin.logentry" pk="4"><field name="action_time" type="DateTimeField">2021-11-06T22:15:48.615000+00:00</field><field name="user" rel="ManyToOneRel" to="chapter_3.seller">1</field><field name="content_type" rel="ManyToOneRel" to="contenttypes.contenttype">13</field><field name="object_id" type="TextField">1</field><field name="object_repr" type="CharField">3.6L DI DOHC 6cyl</field><field name="action_flag" type="PositiveSmallIntegerField">2</field><field name="change_message" type="TextField">[]</field></object><object model="admin.logentry" pk="5"><field name="action_time" type="DateTimeField">2021-11-07T19:31:11.557000+00:00</field><field name="user" rel="ManyToOneRel" to="chapter_3.seller">1</field><field name="content_type" rel="ManyToOneRel" to="contenttypes.contenttype">12</field><field name="object_id" type="TextField">2</field><field name="object_repr" type="CharField">test</field><field name="action_flag" type="PositiveSmallIntegerField">3</field><field name="change_message" type="TextField"></field></object><object model="admin.logentry" pk="6"><field name="action_time" type="DateTimeField">2021-11-07T19:58:19.325000+00:00</field><field name="user" rel="ManyToOneRel" to="chapter_3.seller">1</field><field name="content_type" rel="ManyToOneRel" to="contenttypes.contenttype">12</field><field name="object_id" type="TextField">3</field><field name="object_repr" type="CharField">test</field><field name="action_flag" type="PositiveSmallIntegerField">2</field><field name="change_message" type="TextField">[{"changed": {"fields": ["User permissions"]}}]</field></object><object model="admin.logentry" pk="7"><field name="action_time" type="DateTimeField">2021-11-07T20:37:59.068000+00:00</field><field name="user" rel="ManyToOneRel" to="chapter_3.seller">1</field><field name="content_type" rel="ManyToOneRel" to="contenttypes.contenttype">3</field><field name="object_id" type="TextField">1</field><field name="object_repr" type="CharField">test_group</field><field name="action_flag" type="PositiveSmallIntegerField">1</field><field name="change_message" type="TextField">[{"added": {}}]</field></object><object model="admin.logentry" pk="8"><field name="action_time" type="DateTimeField">2021-11-07T20:39:09.221000+00:00</field><field name="user" rel="ManyToOneRel" to="chapter_3.seller">1</field><field name="content_type" rel="ManyToOneRel" to="contenttypes.contenttype">12</field><field name="object_id" type="TextField">3</field><field name="object_repr" type="CharField">test</field><field name="action_flag" type="PositiveSmallIntegerField">2</field><field name="change_message" type="TextField">[{"changed": {"fields": ["Groups", "User permissions"]}}]</field></object><object model="admin.logentry" pk="9"><field name="action_time" type="DateTimeField">2021-11-29T23:53:13.574000+00:00</field><field name="user" rel="ManyToOneRel" to="chapter_3.seller">1</field><field name="content_type" rel="ManyToOneRel" to="contenttypes.contenttype">12</field><field name="object_id" type="TextField">1</field><field name="object_repr" type="CharField">admin</field><field name="action_flag" type="PositiveSmallIntegerField">2</field><field name="change_message" type="TextField">[{"changed": {"fields": ["First name"]}}]</field></object><object model="admin.logentry" pk="10"><field name="action_time" type="DateTimeField">2021-12-01T23:15:35.843000+00:00</field><field name="user" rel="ManyToOneRel" to="chapter_3.seller">1</field><field name="content_type" rel="ManyToOneRel" to="contenttypes.contenttype">12</field><field name="object_id" type="TextField">1</field><field name="object_repr" type="CharField">admin</field><field name="action_flag" type="PositiveSmallIntegerField">2</field><field name="change_message" type="TextField">[{"changed": {"fields": ["Superuser status", "User permissions"]}}]</field></object><object model="admin.logentry" pk="11"><field name="action_time" type="DateTimeField">2021-12-03T22:36:30.302000+00:00</field><field name="user" rel="ManyToOneRel" to="chapter_3.seller">1</field><field name="content_type" rel="ManyToOneRel" to="contenttypes.contenttype">12</field><field name="object_id" type="TextField">1</field><field name="object_repr" type="CharField">admin</field><field name="action_flag" type="PositiveSmallIntegerField">2</field><field name="change_message" type="TextField">[{"changed": {"fields": ["User permissions"]}}]</field></object><object model="admin.logentry" pk="12"><field name="action_time" type="DateTimeField">2021-12-03T22:39:42.176000+00:00</field><field name="user" rel="ManyToOneRel" to="chapter_3.seller">4</field><field name="content_type" rel="ManyToOneRel" to="contenttypes.contenttype">12</field><field name="object_id" type="TextField">1</field><field name="object_repr" type="CharField">admin</field><field name="action_flag" type="PositiveSmallIntegerField">2</field><field name="change_message" type="TextField">[{"changed": {"fields": ["User permissions"]}}]</field></object><object model="admin.logentry" pk="13"><field name="action_time" type="DateTimeField">2021-12-03T22:43:34.510000+00:00</field><field name="user" rel="ManyToOneRel" to="chapter_3.seller">4</field><field name="content_type" rel="ManyToOneRel" to="contenttypes.contenttype">12</field><field name="object_id" type="TextField">1</field><field name="object_repr" type="CharField">admin</field><field name="action_flag" type="PositiveSmallIntegerField">2</field><field name="change_message" type="TextField">[{"changed": {"fields": ["Superuser status", "User permissions"]}}]</field></object><object model="admin.logentry" pk="14"><field name="action_time" type="DateTimeField">2021-12-03T22:44:30.363000+00:00</field><field name="user" rel="ManyToOneRel" to="chapter_3.seller">4</field><field name="content_type" rel="ManyToOneRel" to="contenttypes.contenttype">12</field><field name="object_id" type="TextField">1</field><field name="object_repr" type="CharField">admin</field><field name="action_flag" type="PositiveSmallIntegerField">2</field><field name="change_message" type="TextField">[{"changed": {"fields": ["Superuser status", "User permissions"]}}]</field></object><object model="admin.logentry" pk="15"><field name="action_time" type="DateTimeField">2021-12-03T22:44:49.348000+00:00</field><field name="user" rel="ManyToOneRel" to="chapter_3.seller">4</field><field name="content_type" rel="ManyToOneRel" to="contenttypes.contenttype">12</field><field name="object_id" type="TextField">1</field><field name="object_repr" type="CharField">admin</field><field name="action_flag" type="PositiveSmallIntegerField">2</field><field name="change_message" type="TextField">[{"changed": {"fields": ["User permissions"]}}]</field></object><object model="admin.logentry" pk="16"><field name="action_time" type="DateTimeField">2021-12-03T22:44:51.733000+00:00</field><field name="user" rel="ManyToOneRel" to="chapter_3.seller">4</field><field name="content_type" rel="ManyToOneRel" to="contenttypes.contenttype">12</field><field name="object_id" type="TextField">1</field><field name="object_repr" type="CharField">admin</field><field name="action_flag" type="PositiveSmallIntegerField">2</field><field name="change_message" type="TextField">[]</field></object><object model="admin.logentry" pk="17"><field name="action_time" type="DateTimeField">2021-12-03T22:44:55.223000+00:00</field><field name="user" rel="ManyToOneRel" to="chapter_3.seller">4</field><field name="content_type" rel="ManyToOneRel" to="contenttypes.contenttype">12</field><field name="object_id" type="TextField">1</field><field name="object_repr" type="CharField">admin</field><field name="action_flag" type="PositiveSmallIntegerField">2</field><field name="change_message" type="TextField">[]</field></object><object model="admin.logentry" pk="18"><field name="action_time" type="DateTimeField">2021-12-03T22:45:04.763000+00:00</field><field name="user" rel="ManyToOneRel" to="chapter_3.seller">4</field><field name="content_type" rel="ManyToOneRel" to="contenttypes.contenttype">12</field><field name="object_id" type="TextField">1</field><field name="object_repr" type="CharField">admin</field><field name="action_flag" type="PositiveSmallIntegerField">2</field><field name="change_message" type="TextField">[]</field></object><object model="admin.logentry" pk="19"><field name="action_time" type="DateTimeField">2021-12-03T22:45:05.870000+00:00</field><field name="user" rel="ManyToOneRel" to="chapter_3.seller">4</field><field name="content_type" rel="ManyToOneRel" to="contenttypes.contenttype">12</field><field name="object_id" type="TextField">1</field><field name="object_repr" type="CharField">admin</field><field name="action_flag" type="PositiveSmallIntegerField">2</field><field name="change_message" type="TextField">[]</field></object><object model="admin.logentry" pk="20"><field name="action_time" type="DateTimeField">2021-12-03T22:45:06.416000+00:00</field><field name="user" rel="ManyToOneRel" to="chapter_3.seller">4</field><field name="content_type" rel="ManyToOneRel" to="contenttypes.contenttype">12</field><field name="object_id" type="TextField">1</field><field name="object_repr" type="CharField">admin</field><field name="action_flag" type="PositiveSmallIntegerField">2</field><field name="change_message" type="TextField">[]</field></object><object model="admin.logentry" pk="21"><field name="action_time" type="DateTimeField">2021-12-03T22:45:06.986000+00:00</field><field name="user" rel="ManyToOneRel" to="chapter_3.seller">4</field><field name="content_type" rel="ManyToOneRel" to="contenttypes.contenttype">12</field><field name="object_id" type="TextField">1</field><field name="object_repr" type="CharField">admin</field><field name="action_flag" type="PositiveSmallIntegerField">2</field><field name="change_message" type="TextField">[]</field></object><object model="admin.logentry" pk="22"><field name="action_time" type="DateTimeField">2021-12-03T22:45:20.414000+00:00</field><field name="user" rel="ManyToOneRel" to="chapter_3.seller">4</field><field name="content_type" rel="ManyToOneRel" to="contenttypes.contenttype">12</field><field name="object_id" type="TextField">1</field><field name="object_repr" type="CharField">admin</field><field name="action_flag" type="PositiveSmallIntegerField">2</field><field name="change_message" type="TextField">[]</field></object><object model="admin.logentry" pk="23"><field name="action_time" type="DateTimeField">2021-12-03T22:54:47.024000+00:00</field><field name="user" rel="ManyToOneRel" to="chapter_3.seller">4</field><field name="content_type" rel="ManyToOneRel" to="contenttypes.contenttype">12</field><field name="object_id" type="TextField">1</field><field name="object_repr" type="CharField">admin</field><field name="action_flag" type="PositiveSmallIntegerField">2</field><field name="change_message" type="TextField">[{"changed": {"fields": ["User permissions"]}}]</field></object><object model="admin.logentry" pk="24"><field name="action_time" type="DateTimeField">2021-12-03T23:37:44.897000+00:00</field><field name="user" rel="ManyToOneRel" to="chapter_3.seller">4</field><field name="content_type" rel="ManyToOneRel" to="contenttypes.contenttype">12</field><field name="object_id" type="TextField">1</field><field name="object_repr" type="CharField">admin</field><field name="action_flag" type="PositiveSmallIntegerField">2</field><field name="change_message" type="TextField">[{"changed": {"fields": ["User permissions"]}}]</field></object><object model="admin.logentry" pk="25"><field name="action_time" type="DateTimeField">2021-12-03T23:45:28.323000+00:00</field><field name="user" rel="ManyToOneRel" to="chapter_3.seller">4</field><field name="content_type" rel="ManyToOneRel" to="contenttypes.contenttype">12</field><field name="object_id" type="TextField">1</field><field name="object_repr" type="CharField">admin</field><field name="action_flag" type="PositiveSmallIntegerField">2</field><field name="change_message" type="TextField">[{"changed": {"fields": ["User permissions"]}}]</field></object><object model="admin.logentry" pk="26"><field name="action_time" type="DateTimeField">2021-12-04T00:03:22.589000+00:00</field><field name="user" rel="ManyToOneRel" to="chapter_3.seller">4</field><field name="content_type" rel="ManyToOneRel" to="contenttypes.contenttype">11</field><field name="object_id" type="TextField">1</field><field name="object_repr" type="CharField">fdd62fe5a4ed36ceed3b9a39656b0c0dc7da6b3d</field><field name="action_flag" type="PositiveSmallIntegerField">1</field><field name="change_message" type="TextField">[{"added": {}}]</field></object><object model="admin.logentry" pk="27"><field name="action_time" type="DateTimeField">2021-12-04T00:03:40.783000+00:00</field><field name="user" rel="ManyToOneRel" to="chapter_3.seller">4</field><field name="content_type" rel="ManyToOneRel" to="contenttypes.contenttype">11</field><field name="object_id" type="TextField">1</field><field name="object_repr" type="CharField">fdd62fe5a4ed36ceed3b9a39656b0c0dc7da6b3d</field><field name="action_flag" type="PositiveSmallIntegerField">3</field><field name="change_message" type="TextField"></field></object><object model="admin.logentry" pk="28"><field name="action_time" type="DateTimeField">2021-12-04T00:18:51.027000+00:00</field><field name="user" rel="ManyToOneRel" to="chapter_3.seller">4</field><field name="content_type" rel="ManyToOneRel" to="contenttypes.contenttype">11</field><field name="object_id" type="TextField">1</field><field name="object_repr" type="CharField">d237fd8092ef4725a14b6febf43637ff623f0925</field><field name="action_flag" type="PositiveSmallIntegerField">1</field><field name="change_message" type="TextField">[{"added": {}}]</field></object><object model="admin.logentry" pk="29"><field name="action_time" type="DateTimeField">2021-12-04T02:14:53.067000+00:00</field><field name="user" rel="ManyToOneRel" to="chapter_3.seller">4</field><field name="content_type" rel="ManyToOneRel" to="contenttypes.contenttype">12</field><field name="object_id" type="TextField">1</field><field name="object_repr" type="CharField">admin</field><field name="action_flag" type="PositiveSmallIntegerField">2</field><field name="change_message" type="TextField">[{"changed": {"fields": ["Staff status"]}}]</field></object><object model="admin.logentry" pk="30"><field name="action_time" type="DateTimeField">2021-12-04T02:17:39.942000+00:00</field><field name="user" rel="ManyToOneRel" to="chapter_3.seller">4</field><field name="content_type" rel="ManyToOneRel" to="contenttypes.contenttype">12</field><field name="object_id" type="TextField">1</field><field name="object_repr" type="CharField">admin</field><field name="action_flag" type="PositiveSmallIntegerField">2</field><field name="change_message" type="TextField">[{"changed": {"fields": ["Staff status"]}}]</field></object><object model="admin.logentry" pk="31"><field name="action_time" type="DateTimeField">2021-12-04T02:18:08.432000+00:00</field><field name="user" rel="ManyToOneRel" to="chapter_3.seller">4</field><field name="content_type" rel="ManyToOneRel" to="contenttypes.contenttype">12</field><field name="object_id" type="TextField">1</field><field name="object_repr" type="CharField">admin</field><field name="action_flag" type="PositiveSmallIntegerField">2</field><field name="change_message" type="TextField">[{"changed": {"fields": ["Staff status"]}}]</field></object><object model="admin.logentry" pk="32"><field name="action_time" type="DateTimeField">2021-12-04T02:19:05.788000+00:00</field><field name="user" rel="ManyToOneRel" to="chapter_3.seller">4</field><field name="content_type" rel="ManyToOneRel" to="contenttypes.contenttype">12</field><field name="object_id" type="TextField">1</field><field name="object_repr" type="CharField">admin</field><field name="action_flag" type="PositiveSmallIntegerField">2</field><field name="change_message" type="TextField">[{"changed": {"fields": ["Staff status"]}}]</field></object><object model="admin.logentry" pk="33"><field name="action_time" type="DateTimeField">2021-12-04T02:19:47.255000+00:00</field><field name="user" rel="ManyToOneRel" to="chapter_3.seller">4</field><field name="content_type" rel="ManyToOneRel" to="contenttypes.contenttype">12</field><field name="object_id" type="TextField">1</field><field name="object_repr" type="CharField">admin</field><field name="action_flag" type="PositiveSmallIntegerField">2</field><field name="change_message" type="TextField">[{"changed": {"fields": ["Staff status", "Last login"]}}]</field></object><object model="admin.logentry" pk="34"><field name="action_time" type="DateTimeField">2021-12-04T02:21:22.341000+00:00</field><field name="user" rel="ManyToOneRel" to="chapter_3.seller">4</field><field name="content_type" rel="ManyToOneRel" to="contenttypes.contenttype">12</field><field name="object_id" type="TextField">1</field><field name="object_repr" type="CharField">admin</field><field name="action_flag" type="PositiveSmallIntegerField">2</field><field name="change_message" type="TextField">[{"changed": {"fields": ["Staff status"]}}]</field></object><object model="admin.logentry" pk="35"><field name="action_time" type="DateTimeField">2021-12-04T02:52:14.016000+00:00</field><field name="user" rel="ManyToOneRel" to="chapter_3.seller">4</field><field name="content_type" rel="ManyToOneRel" to="contenttypes.contenttype">12</field><field name="object_id" type="TextField">1</field><field name="object_repr" type="CharField">admin</field><field name="action_flag" type="PositiveSmallIntegerField">2</field><field name="change_message" type="TextField">[{"changed": {"fields": ["Superuser status", "User permissions"]}}]</field></object><object model="admin.logentry" pk="36"><field name="action_time" type="DateTimeField">2021-12-04T02:54:58.435000+00:00</field><field name="user" rel="ManyToOneRel" to="chapter_3.seller">4</field><field name="content_type" rel="ManyToOneRel" to="contenttypes.contenttype">12</field><field name="object_id" type="TextField">3</field><field name="object_repr" type="CharField">test</field><field name="action_flag" type="PositiveSmallIntegerField">2</field><field name="change_message" type="TextField">[{"changed": {"fields": ["User permissions"]}}]</field></object><object model="admin.logentry" pk="37"><field name="action_time" type="DateTimeField">2021-12-04T02:56:36.984000+00:00</field><field name="user" rel="ManyToOneRel" to="chapter_3.seller">4</field><field name="content_type" rel="ManyToOneRel" to="contenttypes.contenttype">11</field><field name="object_id" type="TextField">3</field><field name="object_repr" type="CharField">fd9191f7d80770014d9e2824693bfbcf9225a020</field><field name="action_flag" type="PositiveSmallIntegerField">1</field><field name="change_message" type="TextField">[{"added": {}}]</field></object><object model="admin.logentry" pk="38"><field name="action_time" type="DateTimeField">2021-12-04T02:57:50.339000+00:00</field><field name="user" rel="ManyToOneRel" to="chapter_3.seller">4</field><field name="content_type" rel="ManyToOneRel" to="contenttypes.contenttype">12</field><field name="object_id" type="TextField">3</field><field name="object_repr" type="CharField">test</field><field name="action_flag" type="PositiveSmallIntegerField">2</field><field name="change_message" type="TextField">[{"changed": {"fields": ["Groups", "User permissions"]}}]</field></object><object model="admin.logentry" pk="39"><field name="action_time" type="DateTimeField">2021-12-04T03:35:53.582000+00:00</field><field name="user" rel="ManyToOneRel" to="chapter_3.seller">4</field><field name="content_type" rel="ManyToOneRel" to="contenttypes.contenttype">12</field><field name="object_id" type="TextField">3</field><field name="object_repr" type="CharField">test</field><field name="action_flag" type="PositiveSmallIntegerField">2</field><field name="change_message" type="TextField">[{"changed": {"fields": ["User permissions"]}}]</field></object><object model="admin.logentry" pk="40"><field name="action_time" type="DateTimeField">2021-12-04T03:40:20.855000+00:00</field><field name="user" rel="ManyToOneRel" to="chapter_3.seller">4</field><field name="content_type" rel="ManyToOneRel" to="contenttypes.contenttype">12</field><field name="object_id" type="TextField">3</field><field name="object_repr" type="CharField">test</field><field name="action_flag" type="PositiveSmallIntegerField">2</field><field name="change_message" type="TextField">[{"changed": {"fields": ["User permissions"]}}]</field></object><object model="admin.logentry" pk="41"><field name="action_time" type="DateTimeField">2021-12-04T03:40:34.704000+00:00</field><field name="user" rel="ManyToOneRel" to="chapter_3.seller">4</field><field name="content_type" rel="ManyToOneRel" to="contenttypes.contenttype">12</field><field name="object_id" type="TextField">3</field><field name="object_repr" type="CharField">test</field><field name="action_flag" type="PositiveSmallIntegerField">2</field><field name="change_message" type="TextField">[{"changed": {"fields": ["User permissions"]}}]</field></object><object model="admin.logentry" pk="42"><field name="action_time" type="DateTimeField">2021-12-04T03:46:50.973000+00:00</field><field name="user" rel="ManyToOneRel" to="chapter_3.seller">4</field><field name="content_type" rel="ManyToOneRel" to="contenttypes.contenttype">12</field><field name="object_id" type="TextField">3</field><field name="object_repr" type="CharField">test</field><field name="action_flag" type="PositiveSmallIntegerField">2</field><field name="change_message" type="TextField">[{"changed": {"fields": ["Staff status"]}}]</field></object><object model="admin.logentry" pk="43"><field name="action_time" type="DateTimeField">2021-12-04T04:23:46.550000+00:00</field><field name="user" rel="ManyToOneRel" to="chapter_3.seller">4</field><field name="content_type" rel="ManyToOneRel" to="contenttypes.contenttype">12</field><field name="object_id" type="TextField">1</field><field name="object_repr" type="CharField">admin</field><field name="action_flag" type="PositiveSmallIntegerField">2</field><field name="change_message" type="TextField">[{"changed": {"fields": ["User permissions"]}}]</field></object><object model="admin.logentry" pk="44"><field name="action_time" type="DateTimeField">2021-12-04T04:24:01.785000+00:00</field><field name="user" rel="ManyToOneRel" to="chapter_3.seller">4</field><field name="content_type" rel="ManyToOneRel" to="contenttypes.contenttype">12</field><field name="object_id" type="TextField">1</field><field name="object_repr" type="CharField">admin</field><field name="action_flag" type="PositiveSmallIntegerField">2</field><field name="change_message" type="TextField">[{"changed": {"fields": ["User permissions"]}}]</field></object><object model="auth.permission" pk="1"><field name="name" type="CharField">Can add log entry</field><field name="content_type" rel="ManyToOneRel" to="contenttypes.contenttype">1</field><field name="codename" type="CharField">add_logentry</field></object><object model="auth.permission" pk="2"><field name="name" type="CharField">Can change log entry</field><field name="content_type" rel="ManyToOneRel" to="contenttypes.contenttype">1</field><field name="codename" type="CharField">change_logentry</field></object><object model="auth.permission" pk="3"><field name="name" type="CharField">Can delete log entry</field><field name="content_type" rel="ManyToOneRel" to="contenttypes.contenttype">1</field><field name="codename" type="CharField">delete_logentry</field></object><object model="auth.permission" pk="4"><field name="name" type="CharField">Can view log entry</field><field name="content_type" rel="ManyToOneRel" to="contenttypes.contenttype">1</field><field name="codename" type="CharField">view_logentry</field></object><object model="auth.permission" pk="5"><field name="name" type="CharField">Can add permission</field><field name="content_type" rel="ManyToOneRel" to="contenttypes.contenttype">2</field><field name="codename" type="CharField">add_permission</field></object><object model="auth.permission" pk="6"><field name="name" type="CharField">Can change permission</field><field name="content_type" rel="ManyToOneRel" to="contenttypes.contenttype">2</field><field name="codename" type="CharField">change_permission</field></object><object model="auth.permission" pk="7"><field name="name" type="CharField">Can delete permission</field><field name="content_type" rel="ManyToOneRel" to="contenttypes.contenttype">2</field><field name="codename" type="CharField">delete_permission</field></object><object model="auth.permission" pk="8"><field name="name" type="CharField">Can view permission</field><field name="content_type" rel="ManyToOneRel" to="contenttypes.contenttype">2</field><field name="codename" type="CharField">view_permission</field></object><object model="auth.permission" pk="9"><field name="name" type="CharField">Can add group</field><field name="content_type" rel="ManyToOneRel" to="contenttypes.contenttype">3</field><field name="codename" type="CharField">add_group</field></object><object model="auth.permission" pk="10"><field name="name" type="CharField">Can change group</field><field name="content_type" rel="ManyToOneRel" to="contenttypes.contenttype">3</field><field name="codename" type="CharField">change_group</field></object><object model="auth.permission" pk="11"><field name="name" type="CharField">Can delete group</field><field name="content_type" rel="ManyToOneRel" to="contenttypes.contenttype">3</field><field name="codename" type="CharField">delete_group</field></object><object model="auth.permission" pk="12"><field name="name" type="CharField">Can view group</field><field name="content_type" rel="ManyToOneRel" to="contenttypes.contenttype">3</field><field name="codename" type="CharField">view_group</field></object><object model="auth.permission" pk="13"><field name="name" type="CharField">Can add content type</field><field name="content_type" rel="ManyToOneRel" to="contenttypes.contenttype">4</field><field name="codename" type="CharField">add_contenttype</field></object><object model="auth.permission" pk="14"><field name="name" type="CharField">Can change content type</field><field name="content_type" rel="ManyToOneRel" to="contenttypes.contenttype">4</field><field name="codename" type="CharField">change_contenttype</field></object><object model="auth.permission" pk="15"><field name="name" type="CharField">Can delete content type</field><field name="content_type" rel="ManyToOneRel" to="contenttypes.contenttype">4</field><field name="codename" type="CharField">delete_contenttype</field></object><object model="auth.permission" pk="16"><field name="name" type="CharField">Can view content type</field><field name="content_type" rel="ManyToOneRel" to="contenttypes.contenttype">4</field><field name="codename" type="CharField">view_contenttype</field></object><object model="auth.permission" pk="17"><field name="name" type="CharField">Can add session</field><field name="content_type" rel="ManyToOneRel" to="contenttypes.contenttype">5</field><field name="codename" type="CharField">add_session</field></object><object model="auth.permission" pk="18"><field name="name" type="CharField">Can change session</field><field name="content_type" rel="ManyToOneRel" to="contenttypes.contenttype">5</field><field name="codename" type="CharField">change_session</field></object><object model="auth.permission" pk="19"><field name="name" type="CharField">Can delete session</field><field name="content_type" rel="ManyToOneRel" to="contenttypes.contenttype">5</field><field name="codename" type="CharField">delete_session</field></object><object model="auth.permission" pk="20"><field name="name" type="CharField">Can view session</field><field name="content_type" rel="ManyToOneRel" to="contenttypes.contenttype">5</field><field name="codename" type="CharField">view_session</field></object><object model="auth.permission" pk="21"><field name="name" type="CharField">Can add address</field><field name="content_type" rel="ManyToOneRel" to="contenttypes.contenttype">6</field><field name="codename" type="CharField">add_address</field></object><object model="auth.permission" pk="22"><field name="name" type="CharField">Can change address</field><field name="content_type" rel="ManyToOneRel" to="contenttypes.contenttype">6</field><field name="codename" type="CharField">change_address</field></object><object model="auth.permission" pk="23"><field name="name" type="CharField">Can delete address</field><field name="content_type" rel="ManyToOneRel" to="contenttypes.contenttype">6</field><field name="codename" type="CharField">delete_address</field></object><object model="auth.permission" pk="24"><field name="name" type="CharField">Can view address</field><field name="content_type" rel="ManyToOneRel" to="contenttypes.contenttype">6</field><field name="codename" type="CharField">view_address</field></object><object model="auth.permission" pk="25"><field name="name" type="CharField">Can add country</field><field name="content_type" rel="ManyToOneRel" to="contenttypes.contenttype">7</field><field name="codename" type="CharField">add_country</field></object><object model="auth.permission" pk="26"><field name="name" type="CharField">Can change country</field><field name="content_type" rel="ManyToOneRel" to="contenttypes.contenttype">7</field><field name="codename" type="CharField">change_country</field></object><object model="auth.permission" pk="27"><field name="name" type="CharField">Can delete country</field><field name="content_type" rel="ManyToOneRel" to="contenttypes.contenttype">7</field><field name="codename" type="CharField">delete_country</field></object><object model="auth.permission" pk="28"><field name="name" type="CharField">Can view country</field><field name="content_type" rel="ManyToOneRel" to="contenttypes.contenttype">7</field><field name="codename" type="CharField">view_country</field></object><object model="auth.permission" pk="29"><field name="name" type="CharField">Can add locality</field><field name="content_type" rel="ManyToOneRel" to="contenttypes.contenttype">8</field><field name="codename" type="CharField">add_locality</field></object><object model="auth.permission" pk="30"><field name="name" type="CharField">Can change locality</field><field name="content_type" rel="ManyToOneRel" to="contenttypes.contenttype">8</field><field name="codename" type="CharField">change_locality</field></object><object model="auth.permission" pk="31"><field name="name" type="CharField">Can delete locality</field><field name="content_type" rel="ManyToOneRel" to="contenttypes.contenttype">8</field><field name="codename" type="CharField">delete_locality</field></object><object model="auth.permission" pk="32"><field name="name" type="CharField">Can view locality</field><field name="content_type" rel="ManyToOneRel" to="contenttypes.contenttype">8</field><field name="codename" type="CharField">view_locality</field></object><object model="auth.permission" pk="33"><field name="name" type="CharField">Can add state</field><field name="content_type" rel="ManyToOneRel" to="contenttypes.contenttype">9</field><field name="codename" type="CharField">add_state</field></object><object model="auth.permission" pk="34"><field name="name" type="CharField">Can change state</field><field name="content_type" rel="ManyToOneRel" to="contenttypes.contenttype">9</field><field name="codename" type="CharField">change_state</field></object><object model="auth.permission" pk="35"><field name="name" type="CharField">Can delete state</field><field name="content_type" rel="ManyToOneRel" to="contenttypes.contenttype">9</field><field name="codename" type="CharField">delete_state</field></object><object model="auth.permission" pk="36"><field name="name" type="CharField">Can view state</field><field name="content_type" rel="ManyToOneRel" to="contenttypes.contenttype">9</field><field name="codename" type="CharField">view_state</field></object><object model="auth.permission" pk="37"><field name="name" type="CharField">Can add Token</field><field name="content_type" rel="ManyToOneRel" to="contenttypes.contenttype">10</field><field name="codename" type="CharField">add_token</field></object><object model="auth.permission" pk="38"><field name="name" type="CharField">Can change Token</field><field name="content_type" rel="ManyToOneRel" to="contenttypes.contenttype">10</field><field name="codename" type="CharField">change_token</field></object><object model="auth.permission" pk="39"><field name="name" type="CharField">Can delete Token</field><field name="content_type" rel="ManyToOneRel" to="contenttypes.contenttype">10</field><field name="codename" type="CharField">delete_token</field></object><object model="auth.permission" pk="40"><field name="name" type="CharField">Can view Token</field><field name="content_type" rel="ManyToOneRel" to="contenttypes.contenttype">10</field><field name="codename" type="CharField">view_token</field></object><object model="auth.permission" pk="41"><field name="name" type="CharField">Can add token</field><field name="content_type" rel="ManyToOneRel" to="contenttypes.contenttype">11</field><field name="codename" type="CharField">add_tokenproxy</field></object><object model="auth.permission" pk="42"><field name="name" type="CharField">Can change token</field><field name="content_type" rel="ManyToOneRel" to="contenttypes.contenttype">11</field><field name="codename" type="CharField">change_tokenproxy</field></object><object model="auth.permission" pk="43"><field name="name" type="CharField">Can delete token</field><field name="content_type" rel="ManyToOneRel" to="contenttypes.contenttype">11</field><field name="codename" type="CharField">delete_tokenproxy</field></object><object model="auth.permission" pk="44"><field name="name" type="CharField">Can view token</field><field name="content_type" rel="ManyToOneRel" to="contenttypes.contenttype">11</field><field name="codename" type="CharField">view_tokenproxy</field></object><object model="auth.permission" pk="45"><field name="name" type="CharField">Can add Seller</field><field name="content_type" rel="ManyToOneRel" to="contenttypes.contenttype">12</field><field name="codename" type="CharField">add_seller</field></object><object model="auth.permission" pk="46"><field name="name" type="CharField">Can change Seller</field><field name="content_type" rel="ManyToOneRel" to="contenttypes.contenttype">12</field><field name="codename" type="CharField">change_seller</field></object><object model="auth.permission" pk="47"><field name="name" type="CharField">Can delete Seller</field><field name="content_type" rel="ManyToOneRel" to="contenttypes.contenttype">12</field><field name="codename" type="CharField">delete_seller</field></object><object model="auth.permission" pk="48"><field name="name" type="CharField">Can view Seller</field><field name="content_type" rel="ManyToOneRel" to="contenttypes.contenttype">12</field><field name="codename" type="CharField">view_seller</field></object><object model="auth.permission" pk="49"><field name="name" type="CharField">Can add Engine</field><field name="content_type" rel="ManyToOneRel" to="contenttypes.contenttype">13</field><field name="codename" type="CharField">add_engine</field></object><object model="auth.permission" pk="50"><field name="name" type="CharField">Can change Engine</field><field name="content_type" rel="ManyToOneRel" to="contenttypes.contenttype">13</field><field name="codename" type="CharField">change_engine</field></object><object model="auth.permission" pk="51"><field name="name" type="CharField">Can delete Engine</field><field name="content_type" rel="ManyToOneRel" to="contenttypes.contenttype">13</field><field name="codename" type="CharField">delete_engine</field></object><object model="auth.permission" pk="52"><field name="name" type="CharField">Can view Engine</field><field name="content_type" rel="ManyToOneRel" to="contenttypes.contenttype">13</field><field name="codename" type="CharField">view_engine</field></object><object model="auth.permission" pk="53"><field name="name" type="CharField">Can add Practice Engine</field><field name="content_type" rel="ManyToOneRel" to="contenttypes.contenttype">14</field><field name="codename" type="CharField">add_engine3</field></object><object model="auth.permission" pk="54"><field name="name" type="CharField">Can change Practice Engine</field><field name="content_type" rel="ManyToOneRel" to="contenttypes.contenttype">14</field><field name="codename" type="CharField">change_engine3</field></object><object model="auth.permission" pk="55"><field name="name" type="CharField">Can delete Practice Engine</field><field name="content_type" rel="ManyToOneRel" to="contenttypes.contenttype">14</field><field name="codename" type="CharField">delete_engine3</field></object><object model="auth.permission" pk="56"><field name="name" type="CharField">Can view Practice Engine</field><field name="content_type" rel="ManyToOneRel" to="contenttypes.contenttype">14</field><field name="codename" type="CharField">view_engine3</field></object><object model="auth.permission" pk="57"><field name="name" type="CharField">Can add Vehicle</field><field name="content_type" rel="ManyToOneRel" to="contenttypes.contenttype">15</field><field name="codename" type="CharField">add_vehicle</field></object><object model="auth.permission" pk="58"><field name="name" type="CharField">Can change Vehicle</field><field name="content_type" rel="ManyToOneRel" to="contenttypes.contenttype">15</field><field name="codename" type="CharField">change_vehicle</field></object><object model="auth.permission" pk="59"><field name="name" type="CharField">Can delete Vehicle</field><field name="content_type" rel="ManyToOneRel" to="contenttypes.contenttype">15</field><field name="codename" type="CharField">delete_vehicle</field></object><object model="auth.permission" pk="60"><field name="name" type="CharField">Can view Vehicle</field><field name="content_type" rel="ManyToOneRel" to="contenttypes.contenttype">15</field><field name="codename" type="CharField">view_vehicle</field></object><object model="auth.permission" pk="61"><field name="name" type="CharField">Can add Vehicle Model</field><field name="content_type" rel="ManyToOneRel" to="contenttypes.contenttype">16</field><field name="codename" type="CharField">add_vehicle_model</field></object><object model="auth.permission" pk="62"><field name="name" type="CharField">Can change Vehicle Model</field><field name="content_type" rel="ManyToOneRel" to="contenttypes.contenttype">16</field><field name="codename" type="CharField">change_vehicle_model</field></object><object model="auth.permission" pk="63"><field name="name" type="CharField">Can delete Vehicle Model</field><field name="content_type" rel="ManyToOneRel" to="contenttypes.contenttype">16</field><field name="codename" type="CharField">delete_vehicle_model</field></object><object model="auth.permission" pk="64"><field name="name" type="CharField">Can view Vehicle Model</field><field name="content_type" rel="ManyToOneRel" to="contenttypes.contenttype">16</field><field name="codename" type="CharField">view_vehicle_model</field></object><object model="auth.group" pk="1"><field name="name" type="CharField">test_group</field><field name="permissions" rel="ManyToManyRel" to="auth.permission"><object pk="49"></object><object pk="50"></object><object pk="51"></object><object pk="52"></object><object pk="53"></object><object pk="54"></object><object pk="55"></object><object pk="56"></object><object pk="45"></object><object pk="46"></object><object pk="47"></object><object pk="48"></object><object pk="57"></object><object pk="58"></object><object pk="59"></object><object pk="60"></object><object pk="61"></object><object pk="62"></object><object pk="63"></object><object pk="64"></object></field></object><object model="contenttypes.contenttype" pk="1"><field name="app_label" type="CharField">admin</field><field name="model" type="CharField">logentry</field></object><object model="contenttypes.contenttype" pk="2"><field name="app_label" type="CharField">auth</field><field name="model" type="CharField">permission</field></object><object model="contenttypes.contenttype" pk="3"><field name="app_label" type="CharField">auth</field><field name="model" type="CharField">group</field></object><object model="contenttypes.contenttype" pk="4"><field name="app_label" type="CharField">contenttypes</field><field name="model" type="CharField">contenttype</field></object><object model="contenttypes.contenttype" pk="5"><field name="app_label" type="CharField">sessions</field><field name="model" type="CharField">session</field></object><object model="contenttypes.contenttype" pk="6"><field name="app_label" type="CharField">address</field><field name="model" type="CharField">address</field></object><object model="contenttypes.contenttype" pk="7"><field name="app_label" type="CharField">address</field><field name="model" type="CharField">country</field></object><object model="contenttypes.contenttype" pk="8"><field name="app_label" type="CharField">address</field><field name="model" type="CharField">locality</field></object><object model="contenttypes.contenttype" pk="9"><field name="app_label" type="CharField">address</field><field name="model" type="CharField">state</field></object><object model="contenttypes.contenttype" pk="10"><field name="app_label" type="CharField">authtoken</field><field name="model" type="CharField">token</field></object><object model="contenttypes.contenttype" pk="11"><field name="app_label" type="CharField">authtoken</field><field name="model" type="CharField">tokenproxy</field></object><object model="contenttypes.contenttype" pk="12"><field name="app_label" type="CharField">chapter_3</field><field name="model" type="CharField">seller</field></object><object model="contenttypes.contenttype" pk="13"><field name="app_label" type="CharField">chapter_3</field><field name="model" type="CharField">engine</field></object><object model="contenttypes.contenttype" pk="14"><field name="app_label" type="CharField">chapter_3</field><field name="model" type="CharField">engine3</field></object><object model="contenttypes.contenttype" pk="15"><field name="app_label" type="CharField">chapter_3</field><field name="model" type="CharField">vehicle</field></object><object model="contenttypes.contenttype" pk="16"><field name="app_label" type="CharField">chapter_3</field><field name="model" type="CharField">vehicle_model</field></object><object model="sessions.session" pk="i3jdgkhy0d7ud6h1jroez32w1mt8s7v7"><field name="session_data" type="TextField">.eJxVjMsOwiAQRf-FtSEwlIcu3fcbyDADUjU0Ke3K-O_apAvd3nPOfYmI21rj1vMSJxYXocXpd0tIj9x2wHdst1nS3NZlSnJX5EG7HGfOz-vh_h1U7PVbD2dnuDibtVI6gyIChckwUQAXEoMtBYwBby1yIU-BwYTBcfbBYWLx_gDfrjgq:1muluz:TgRcT6yISna1kX5v7l4GycSzb8RhQICMg_gZdKX_zzc</field><field name="expire_date" type="DateTimeField">2021-12-22T01:38:49.433221+00:00</field></object><object model="sessions.session" pk="ixmkpqnrjepft0wk37exl4w9295tb02s"><field name="session_data" type="TextField">.eJxVjMsOwiAQRf-FtSEwlIcu3fcbyDADUjU0Ke3K-O_apAvd3nPOfYmI21rj1vMSJxYXocXpd0tIj9x2wHdst1nS3NZlSnJX5EG7HGfOz-vh_h1U7PVbD2dnuDibtVI6gyIChckwUQAXEoMtBYwBby1yIU-BwYTBcfbBYWLx_gDfrjgq:1mzTnb:tA0sBd5GTQzNlHjkChksO_6cLhCfLgX_SMutQ9qtDYM</field><field name="expire_date" type="DateTimeField">2022-01-04T01:18:39.943619+00:00</field></object><object model="authtoken.token" pk="d237fd8092ef4725a14b6febf43637ff623f0925"><field name="user" rel="OneToOneRel" to="chapter_3.seller">1</field><field name="created" type="DateTimeField">2021-12-04T00:18:50.998000+00:00</field></object><object model="authtoken.token" pk="fd9191f7d80770014d9e2824693bfbcf9225a020"><field name="user" rel="OneToOneRel" to="chapter_3.seller">3</field><field name="created" type="DateTimeField">2021-12-04T02:56:36.935000+00:00</field></object><object model="chapter_3.vehicle_model" pk="1"><field name="name" type="CharField">Envision Avenir</field><field name="make" type="PositiveIntegerField">1</field></object><object model="chapter_3.vehicle_model" pk="2"><field name="name" type="CharField">Enclave Avenir</field><field name="make" type="PositiveIntegerField">1</field></object><object model="chapter_3.vehicle_model" pk="3"><field name="name" type="CharField">Blazer LT</field><field name="make" type="PositiveIntegerField">3</field></object><object model="chapter_3.engine" pk="1"><field name="name" type="CharField">3.6L DI DOHC 6cyl</field><field name="vehicle_model" rel="ManyToOneRel" to="chapter_3.vehicle_model">2</field></object><object model="chapter_3.engine" pk="2"><field name="name" type="CharField">3.9L DI DOHC 6cyl</field><field name="vehicle_model" rel="ManyToOneRel" to="chapter_3.vehicle_model">3</field></object><object model="chapter_3.vehicle" pk="1"><field name="vin" type="CharField">aa123456789012345</field><field name="sold" type="BooleanField">True</field><field name="price_currency" type="CharField">USD</field><field name="price" type="DecimalField">